[
   {
      "leagueId" : null,
      "createdAt" : "2019-06-12T11:12:32.302Z",
      "id" : 1,
      "updatedAt" : "2019-06-12T11:12:32.302Z",
      "name" : "Griffin"
   },
   {
      "leagueId" : null,
      "createdAt" : "2019-06-12T11:12:50.110Z",
      "id" : 2,
      "updatedAt" : "2019-06-12T11:12:50.110Z",
      "name" : "SANDBOX Gaming"
   },
   {
      "updatedAt" : "2019-06-12T11:13:04.264Z",
      "id" : 3,
      "leagueId" : null,
      "createdAt" : "2019-06-12T11:13:04.264Z",
      "name" : "Gen.G"
   },
   {
      "updatedAt" : "2019-06-12T11:13:26.232Z",
      "leagueId" : null,
      "id" : 4,
      "createdAt" : "2019-06-12T11:13:26.232Z",
      "name" : "Jin Air Green Wings"
   },
   {
      "name" : "KINGZONE DragonX",
      "updatedAt" : "2019-06-12T11:13:40.557Z",
      "leagueId" : null,
      "id" : 5,
      "createdAt" : "2019-06-12T11:13:40.557Z"
   },
   {
      "updatedAt" : "2019-06-12T11:13:50.960Z",
      "leagueId" : null,
      "createdAt" : "2019-06-12T11:13:50.960Z",
      "id" : 6,
      "name" : "SK Telecom T1"
   },
   {
      "leagueId" : null,
      "id" : 7,
      "createdAt" : "2019-06-12T11:14:04.595Z",
      "updatedAt" : "2019-06-12T11:14:04.595Z",
      "name" : "KT Rolster"
   },
   {
      "name" : "DAMWON Gaming",
      "updatedAt" : "2019-06-12T11:14:19.247Z",
      "id" : 8,
      "leagueId" : null,
      "createdAt" : "2019-06-12T11:14:19.247Z"
   },
   {
      "updatedAt" : "2019-06-12T11:14:46.857Z",
      "id" : 9,
      "leagueId" : null,
      "createdAt" : "2019-06-12T11:14:46.857Z",
      "name" : "Hanwha Life Esports"
   },
   {
      "id" : 10,
      "leagueId" : null,
      "createdAt" : "2019-06-12T11:15:04.647Z",
      "updatedAt" : "2019-06-12T11:15:04.647Z",
      "name" : "Afreeca Freecs"
   },
   {
      "updatedAt" : "2019-06-12T13:44:48.674Z",
      "leagueId" : null,
      "createdAt" : "2019-06-12T13:44:48.674Z",
      "id" : 11,
      "name" : "Misfits"
   },
   {
      "name" : "Excel Esports",
      "id" : 12,
      "leagueId" : null,
      "createdAt" : "2019-06-12T13:45:04.961Z",
      "updatedAt" : "2019-06-12T13:45:04.961Z"
   },
   {
      "name" : "Rogue",
      "updatedAt" : "2019-06-12T13:45:29.989Z",
      "createdAt" : "2019-06-12T13:45:29.989Z",
      "leagueId" : null,
      "id" : 13
   },
   {
      "name" : "Team Vitality",
      "createdAt" : "2019-06-12T13:45:41.843Z",
      "leagueId" : null,
      "id" : 14,
      "updatedAt" : "2019-06-12T13:45:41.843Z"
   },
   {
      "leagueId" : null,
      "createdAt" : "2019-06-12T13:45:57.000Z",
      "id" : 15,
      "updatedAt" : "2019-06-12T13:45:57.000Z",
      "name" : "Fnatic"
   },
   {
      "name" : "Origen",
      "updatedAt" : "2019-06-12T13:46:04.968Z",
      "leagueId" : null,
      "id" : 16,
      "createdAt" : "2019-06-12T13:46:04.968Z"
   },
   {
      "name" : "G2 Esports",
      "updatedAt" : "2019-06-12T13:46:57.098Z",
      "createdAt" : "2019-06-12T13:46:57.098Z",
      "leagueId" : null,
      "id" : 18
   },
   {
      "name" : "SK Gaming",
      "updatedAt" : "2019-06-12T13:47:21.821Z",
      "leagueId" : null,
      "createdAt" : "2019-06-12T13:47:21.821Z",
      "id" : 19
   },
   {
      "name" : "Splyce",
      "leagueId" : null,
      "id" : 20,
      "createdAt" : "2019-06-12T13:47:39.567Z",
      "updatedAt" : "2019-06-12T13:47:39.567Z"
   },
   {
      "leagueId" : null,
      "id" : 21,
      "createdAt" : "2019-06-12T14:06:00.030Z",
      "updatedAt" : "2019-06-12T14:06:00.030Z",
      "name" : "Chiefs Esports Club"
   },
   {
      "name" : "Gravitas",
      "updatedAt" : "2019-06-12T14:06:08.734Z",
      "leagueId" : null,
      "createdAt" : "2019-06-12T14:06:08.734Z",
      "id" : 22
   },
   {
      "updatedAt" : "2019-06-12T14:06:17.986Z",
      "id" : 23,
      "leagueId" : null,
      "createdAt" : "2019-06-12T14:06:17.986Z",
      "name" : "Avant Gaming"
   },
   {
      "name" : "Legacy",
      "updatedAt" : "2019-06-12T14:06:24.188Z",
      "leagueId" : null,
      "id" : 24,
      "createdAt" : "2019-06-12T14:06:24.188Z"
   },
   {
      "updatedAt" : "2019-06-12T14:06:33.721Z",
      "leagueId" : null,
      "id" : 25,
      "createdAt" : "2019-06-12T14:06:33.721Z",
      "name" : "Dire Wolves"
   },
   {
      "name" : "ORDER",
      "createdAt" : "2019-06-12T14:06:41.425Z",
      "leagueId" : null,
      "id" : 26,
      "updatedAt" : "2019-06-12T14:06:41.425Z"
   },
   {
      "leagueId" : null,
      "id" : 27,
      "createdAt" : "2019-06-12T14:06:52.794Z",
      "updatedAt" : "2019-06-12T14:06:52.794Z",
      "name" : "MAMMOTH"
   },
   {
      "name" : "Bombers",
      "id" : 28,
      "leagueId" : null,
      "createdAt" : "2019-06-12T14:07:00.891Z",
      "updatedAt" : "2019-06-12T14:07:00.891Z"
   },
   {
      "leagueId" : null,
      "createdAt" : "2019-06-12T14:26:15.047Z",
      "id" : 29,
      "updatedAt" : "2019-06-12T14:26:15.047Z",
      "name" : "MAD Lions"
   },
   {
      "name" : "Penguins",
      "updatedAt" : "2019-06-12T14:26:26.623Z",
      "leagueId" : null,
      "createdAt" : "2019-06-12T14:26:26.623Z",
      "id" : 30
   },
   {
      "name" : "eMonkeyz",
      "updatedAt" : "2019-06-12T14:26:37.076Z",
      "id" : 31,
      "leagueId" : null,
      "createdAt" : "2019-06-12T14:26:37.076Z"
   },
   {
      "updatedAt" : "2019-06-12T14:26:46.713Z",
      "leagueId" : null,
      "id" : 32,
      "createdAt" : "2019-06-12T14:26:46.713Z",
      "name" : "Movistar Riders"
   },
   {
      "name" : "G2 Heretics",
      "updatedAt" : "2019-06-12T14:26:57.593Z",
      "id" : 33,
      "leagueId" : null,
      "createdAt" : "2019-06-12T14:26:57.593Z"
   },
   {
      "leagueId" : null,
      "createdAt" : "2019-06-12T14:27:07.600Z",
      "id" : 34,
      "updatedAt" : "2019-06-12T14:27:07.600Z",
      "name" : "Origen BCN"
   },
   {
      "name" : "S2V Esports",
      "updatedAt" : "2019-06-12T14:27:17.646Z",
      "leagueId" : null,
      "createdAt" : "2019-06-12T14:27:17.646Z",
      "id" : 35
   },
   {
      "name" : "Team Queso",
      "id" : 36,
      "leagueId" : null,
      "createdAt" : "2019-06-12T14:27:26.528Z",
      "updatedAt" : "2019-06-12T14:27:26.528Z"
   },
   {
      "leagueId" : null,
      "id" : 37,
      "createdAt" : "2019-06-12T14:27:34.021Z",
      "updatedAt" : "2019-06-12T14:27:34.021Z",
      "name" : "x6tence"
   },
   {
      "name" : "Vodafone Giants",
      "updatedAt" : "2019-06-12T14:27:43.674Z",
      "leagueId" : null,
      "id" : 38,
      "createdAt" : "2019-06-12T14:27:43.674Z"
   },
   {
      "updatedAt" : "2019-06-13T08:44:24.540Z",
      "leagueId" : null,
      "createdAt" : "2019-06-12T13:46:39.986Z",
      "id" : 17,
      "name" : "Schalke 04"
   },
   {
      "updatedAt" : "2019-06-16T08:30:10.068Z",
      "leagueId" : null,
      "id" : 39,
      "createdAt" : "2019-06-16T08:30:10.068Z",
      "name" : "Splyce Vipers"
   },
   {
      "name" : "Vitality.Bee",
      "updatedAt" : "2019-06-16T09:57:03.001Z",
      "id" : 40,
      "leagueId" : null,
      "createdAt" : "2019-06-16T09:57:03.001Z"
   },
   {
      "name" : "ROG Esport",
      "id" : 41,
      "leagueId" : null,
      "createdAt" : "2019-06-16T09:57:21.182Z",
      "updatedAt" : "2019-06-16T09:57:21.182Z"
   },
   {
      "id" : 42,
      "leagueId" : null,
      "createdAt" : "2019-06-16T09:57:38.265Z",
      "updatedAt" : "2019-06-16T09:57:38.265Z",
      "name" : "Team MCES"
   },
   {
      "name" : "LDLC",
      "leagueId" : null,
      "createdAt" : "2019-06-16T09:57:47.328Z",
      "id" : 43,
      "updatedAt" : "2019-06-16T09:57:47.328Z"
   },
   {
      "name" : "against All authority",
      "id" : 44,
      "leagueId" : null,
      "createdAt" : "2019-06-16T09:58:04.778Z",
      "updatedAt" : "2019-06-16T09:58:04.778Z"
   },
   {
      "name" : "Gamers Origin",
      "updatedAt" : "2019-06-16T09:58:20.889Z",
      "createdAt" : "2019-06-16T09:58:20.889Z",
      "leagueId" : null,
      "id" : 45
   },
   {
      "name" : "Solary",
      "updatedAt" : "2019-06-16T09:58:31.207Z",
      "createdAt" : "2019-06-16T09:58:31.207Z",
      "leagueId" : null,
      "id" : 46
   },
   {
      "leagueId" : null,
      "createdAt" : "2019-06-16T09:58:44.186Z",
      "id" : 47,
      "updatedAt" : "2019-06-16T09:58:44.186Z",
      "name" : "Misfits Premier"
   }
]
